solitaire_game/__init__.py
solitaire_game/game.py
solitaire_game/game_ui.py
solitaire_game/main.py
solitaire_game-0.0.11.dist-info/METADATA
solitaire_game-0.0.11.dist-info/WHEEL
solitaire_game-0.0.11.dist-info/entry_points.txt
solitaire_game-0.0.11.dist-info/top_level.txt
solitaire_game-0.0.11.dist-info/RECORD
